jsdoc2json/__init__.py
jsdoc2json/main.py
jsdoc2json/modules/__init__.py
jsdoc2json/modules/jsdoc_data.py
jsdoc2json/modules/lexical_parser.py
jsdoc2json/modules/lexical_regex.py
jsdoc2json/modules/lexical_tokens.py
jsdoc2json/modules/syntax_parser.py
jsdoc2json-1.0.1.dist-info/LICENSE
jsdoc2json-1.0.1.dist-info/METADATA
jsdoc2json-1.0.1.dist-info/WHEEL
jsdoc2json-1.0.1.dist-info/entry_points.txt
jsdoc2json-1.0.1.dist-info/top_level.txt
jsdoc2json-1.0.1.dist-info/RECORD
