Metadata-Version: 2.1
Name: jsdoc2json
Version: 1.0.1
Summary: A Python tool for Game Maker developers to convert JSDoc comments from GML files to JSON.
Home-page: https://github.com/Cooleure/jsdoc2json
Author: Nicolas Dejean
Author-email: nicolasdejean@laposte.net
License: MIT
Classifier: Programming Language :: Python :: 3
Classifier: License :: OSI Approved :: MIT License
Classifier: Operating System :: OS Independent
License-File: LICENSE
